zhangwei_helper/__init__.py
zhangwei_helper/const/Const.py
zhangwei_helper/const/__init__.py
zhangwei_helper/enum/SelfEnum.py
zhangwei_helper/enum/__init__.py
zhangwei_helper/function/Network.py
zhangwei_helper/function/Os.py
zhangwei_helper/function/Regedit.py
zhangwei_helper/function/Software.py
zhangwei_helper/function/TypeCheck.py
zhangwei_helper/function/WindowsService.py
zhangwei_helper/function/__init__.py
zhangwei_helper/test/__init__.py
zhangwei_helper/test/test_function/__init__.py
zhangwei_helper/test/test_function/test_TypeCheck.py
zhangwei_helper-0.0.7.dist-info/LICENSE
zhangwei_helper-0.0.7.dist-info/METADATA
zhangwei_helper-0.0.7.dist-info/WHEEL
zhangwei_helper-0.0.7.dist-info/top_level.txt
zhangwei_helper-0.0.7.dist-info/RECORD
