Metadata-Version: 2.1
Name: zhangwei-helper
Version: 0.0.7
Summary: A package include all common part,like function,enum,written                  by zhangwei(zwzw911)
Home-page: https://github.com/zwzw911/zhangwei_helper
Author: zwzw911
Author-email: zwzw911110@163.com
License: UNKNOWN
Platform: UNKNOWN
Classifier: Programming Language :: Python :: 3
Classifier: License :: OSI Approved :: MIT License
Classifier: Operating System :: Microsoft :: Windows
Requires-Python: >=3.6
